.svnignore
README.txt
create-db.py
dev.cfg
sample-prod.cfg
setup.py
start-gibe.py
update-db.txt
gibe/__init__.py
gibe/akismet.py
gibe/analytics.py
gibe/commenting.py
gibe/controllers.py
gibe/feeds.py
gibe/json.py
gibe/model.py
gibe/plugin.py
gibe/postmarkup.py
gibe/postmarkupsupport.py
gibe/release.py
gibe/syntaxhighlighting.py
gibe/tinymcesupport.py
gibe/util.py
gibe.egg-info/PKG-INFO
gibe.egg-info/SOURCES.txt
gibe.egg-info/dependency_links.txt
gibe.egg-info/entry_points.txt
gibe.egg-info/not-zip-safe
gibe.egg-info/requires.txt
gibe.egg-info/top_level.txt
gibe/bloggingprotheme/__init__.py
gibe/bloggingprotheme/plugin.py
gibe/bloggingprotheme/release.py
gibe/bloggingprotheme/widgets.py
gibe/bloggingprotheme/static/css/style.css
gibe/bloggingprotheme/static/images/ButtonTransparent.png
gibe/bloggingprotheme/static/images/CategIco.png
gibe/bloggingprotheme/static/images/CommentsFormEndBkg.gif
gibe/bloggingprotheme/static/images/CommentsFormHeading.png
gibe/bloggingprotheme/static/images/CommentsFormTopBkg.gif
gibe/bloggingprotheme/static/images/CommentsListHeading.png
gibe/bloggingprotheme/static/images/ExtraIco.png
gibe/bloggingprotheme/static/images/PostComLeft.png
gibe/bloggingprotheme/static/images/PostComRight.png
gibe/bloggingprotheme/static/images/RelatedPostsHeading.png
gibe/bloggingprotheme/static/images/SRBkg.gif
gibe/bloggingprotheme/static/images/SRLBkg.gif
gibe/bloggingprotheme/static/images/SRRBkg.gif
gibe/bloggingprotheme/static/images/SearchBkg.png
gibe/bloggingprotheme/static/images/SearchBkgNone.png
gibe/bloggingprotheme/static/images/SearchButton.png
gibe/bloggingprotheme/static/images/SearchKeyword.png
gibe/bloggingprotheme/static/images/SubmitComment.png
gibe/bloggingprotheme/static/images/SyndicateListBkg.png
gibe/bloggingprotheme/static/images/bkg_body.png
gibe/bloggingprotheme/static/images/feed-icon-64x64.png
gibe/bloggingprotheme/static/images/transparent.gif
gibe/bloggingprotheme/static/javascript/imghover.js
gibe/bloggingprotheme/templates/__init__.py
gibe/bloggingprotheme/templates/archives.html
gibe/bloggingprotheme/templates/frontpage.html
gibe/bloggingprotheme/templates/master.html
gibe/bloggingprotheme/templates/post.html
