Metadata-Version: 1.0
Name: gibe
Version: 0.12.4
Summary: Blog using TurboGears with popular replacement components
Home-page: http://code.google.com/p/gibe/
Author: Neil Blakey-Milner
Author-email: nbm@nxsy.org
License: BSD
Download-URL: http://code.google.com/p/gibe/downloads/list
Keywords: turbogears.app,blog
Platform: UNKNOWN
Classifier: Development Status :: 3 - Alpha
Classifier: Operating System :: OS Independent
Classifier: Programming Language :: Python
Classifier: Framework :: TurboGears
Classifier: Framework :: TurboGears :: Applications
